suspicious/__init__.py
suspicious/cli.py
suspicious/render.py
suspicious/sus.py
suspicious/templates/index.html.j2
suspicious-0.1.1.dist-info/LICENSE.txt
suspicious-0.1.1.dist-info/METADATA
suspicious-0.1.1.dist-info/WHEEL
suspicious-0.1.1.dist-info/entry_points.txt
suspicious-0.1.1.dist-info/top_level.txt
suspicious-0.1.1.dist-info/RECORD
