Metadata-Version: 2.1
Name: suspicious
Version: 0.1.1
Summary: Detects possibly suspicious stuff in your source files
Home-page: https://github.com/sturdy-dev/suspicious
Author: Kiril Videlov
Author-email: kiril@codeball.ai
Keywords: code analysis
Classifier: Development Status :: 3 - Alpha
Classifier: Environment :: Console
Classifier: Intended Audience :: Developers
Classifier: License :: OSI Approved :: GNU Affero General Public License v3
Classifier: Operating System :: OS Independent
Classifier: Programming Language :: Python :: 3
Classifier: Topic :: Software Development
Classifier: Topic :: Utilities
Requires-Python: >=3.8
License-File: LICENSE.txt
Requires-Dist: Jinja2 (==3.1.2)
Requires-Dist: numpy (==1.22.4)
Requires-Dist: setuptools (==65.5.1)
Requires-Dist: torch (==1.12.1)
Requires-Dist: tqdm (==4.64.0)
Requires-Dist: transformers (==4.24.0)
